synapse_super_invites/__init__.py
synapse_super_invites/alembic.ini
synapse_super_invites/config.py
synapse_super_invites/py.typed
synapse_super_invites/migration/env.py
synapse_super_invites/migration/script.py.mako
synapse_super_invites/migration/versions/25e4ec3cea32_added_token_table.py
synapse_super_invites/migration/versions/8c8c90d89eac_add_error_logs_to_acceptance.py
synapse_super_invites/model/__init__.py
synapse_super_invites/resource/__init__.py
synapse_super_invites/resource/base.py
synapse_super_invites/resource/info.py
synapse_super_invites/resource/redeem.py
synapse_super_invites/resource/tokens.py
synapse_super_invites/resource/web_access.py
synapse_super_invites/static/index.html
synapse_super_invites/static/pure-min.css
synapse_super_invites/static/script.js
synapse_super_invites-0.8.4.dist-info/METADATA
synapse_super_invites-0.8.4.dist-info/WHEEL
synapse_super_invites-0.8.4.dist-info/top_level.txt
synapse_super_invites-0.8.4.dist-info/RECORD
