Metadata-Version: 2.1
Name: synapse_super_invites
Version: 0.8.4
Summary: Provides extended support for users to invite other users to rooms via an inventation token
Project-URL: Homepage, https://www.acter.global/
Project-URL: Repository, https://github.com/acterglobal/synapse-super-invites/
Classifier: License :: OSI Approved :: Apache Software License
Requires-Python: >=3.8
Requires-Dist: matrix-synapse
Requires-Dist: sqlalchemy
Requires-Dist: alembic
Requires-Dist: attrs
Provides-Extra: dev
Requires-Dist: tox; extra == "dev"
Requires-Dist: twisted; extra == "dev"
Requires-Dist: matrix-synapse-testutils; extra == "dev"
Requires-Dist: mypy==1.6.1; extra == "dev"
Requires-Dist: black==23.10.0; extra == "dev"
Requires-Dist: ruff==0.1.1; extra == "dev"
Requires-Dist: build; extra == "dev"
Requires-Dist: twine; extra == "dev"
